[
  {
    "title": "Deep",
    "desc": "Patel"
  },
  {
    "title": "deep",
    "desc": "patel"
  },
  {
    "title": "deep",
    "desc": "patel"
  },
  {
    "title": "hi",
    "desc": ""
  },
  {
    "title": "hi",
    "desc": ""
  },
  {
    "title": "hi",
    "desc": ""
  },
  {
    "title": "hi",
    "desc": ""
  },
  {
    "title": "hi",
    "desc": "hello"
  },
  {
    "title": "hi",
    "desc": "hello"
  },
  {
    "title": "hi",
    "desc": "hello"
  },
  {
    "title": "hi",
    "desc": "hello"
  },
  {
    "title": "hi",
    "desc": "hello"
  },
  {
    "title": "abcd",
    "desc": "ABCDE"
  }
]